[
	{
		"name": "musicsdp.com",
		"host": "147.93.73.220",
		"protocol": "sftp",
		"port": 65002,
		"username": "u790318601",
		"password": "Huy@0924900914",
		"remotePath": "/home/u790318601/domains/",
		"uploadOnSave": true,
		"useTempFile": false,
		"openSsh": true
	},
	{
		"name": "Motchill.style",
		"host": "145.223.111.157",
		"protocol": "sftp",
		"port": 65002,
		"username": "u157486133",
		"password": "Huy@0924900914",
		"remotePath": "/home/u157486133/",
		"uploadOnSave": true,
		"useTempFile": false,
		"openSsh": true
	},
	{
		"name": "squarewaveventures.com",
		"host": "145.79.14.13",
		"protocol": "sftp",
		"port": 65002,
		"username": "u819140883",
		"password": "Huy@0924900914",
		"remotePath": "/home/u819140883/domains/squarewaveventures.com",
		"uploadOnSave": true,
		"useTempFile": false,
		"openSsh": true
	},
	{
		"name": "squarewaveventures.com",
		"host": "145.79.14.13",
		"protocol": "sftp",
		"port": 65002,
		"username": "u819140883",
		"password": "Huy@0924900914",
		"remotePath": "/home/u819140883/domains/squarewaveventures.com",
		"uploadOnSave": true,
		"useTempFile": false,
		"openSsh": true
	},
	{
		"name": "37.44.245.228",
		"host": "37.44.245.228",
		"protocol": "sftp",
		"port": 65002,
		"username": "u582626346",
		"password": "Huy@0924900914",
		"remotePath": "/home/u582626346/domains/superstrate.net",
		"uploadOnSave": true,
		"useTempFile": false,
		"openSsh": true
	},
	{
		"name": "Motphimchill + SubNhanh",
		"host": "185.82.73.83",
		"protocol": "sftp",
		"port": 22,
		"username": "admin",
		"password": "CWMYT8h6Ovd7#",
		"agent": "pageant",
		"passphrase": "CWMYT8h6Ovd7#",
		"remotePath": "/home/admin/public_html",
		"uploadOnSave": true,
		"useTempFile": false,
		"openSsh": true,
		"ignore": [
			"**/.vscode/**",
			"**/.git/**",
			"**/node_modules/**",
			"**/.DS_Store"
		]
	},
	{
		"name": "Sport",
		"host": "178.16.132.145",
		"protocol": "sftp",
		"port": 65002,
		"username": "u430157488",
		"password": "CWMYT8h6Ovd7#",
		"agent": "pageant",
		"passphrase": "CWMYT8h6Ovd7#",
		"remotePath": "/home/u430157488/domains/smdoire.ie",
		"uploadOnSave": true,
		"useTempFile": false,
		"openSsh": true,
		"ignore": [
			"**/.vscode/**",
			"**/.git/**",
			"**/node_modules/**",
			"**/.DS_Store"
		]
	}
]